{
  "004": { "name": "Afghanistan", "risk": 77, "issues": ["Sanctions", "Trade restrictions"] },
  "008": { "name": "Albania", "risk": 45, "issues": ["Tariff inconsistencies", "Documentation errors"] },
  "010": { "name": "Antarctica", "risk": 50, "issues": [] },
  "012": { "name": "Algeria", "risk": 66, "issues": ["Import licensing delays", "Foreign currency restrictions"] },
  "016": { "name": "American Samoa", "risk": 50, "issues": [] },
  "020": { "name": "Andorra", "risk": 18, "issues": ["Small trade volume", "Occasional HS misclassification"] },
  "024": { "name": "Angola", "risk": 62, "issues": ["Port congestion", "Valuation disputes"] },
  "028": { "name": "Antigua and Barbuda", "risk": 50, "issues": [] },
  "031": { "name": "Azerbaijan", "risk": 58, "issues": ["Oil-related trade disputes", "Valuation inconsistencies"] },
  "032": { "name": "Argentina", "risk": 71, "issues": ["Customs clearance delays", "Import quotas"] },
  "036": { "name": "Australia", "risk": 29, "issues": ["Biosecurity checks"] },
  "040": { "name": "Austria", "risk": 33, "issues": ["Low risk", "Occasional VAT handling"] },
  "044": { "name": "Bahamas", "risk": 50, "issues": [] },
  "048": { "name": "Bahrain", "risk": 40, "issues": ["Free trade zone checks", "Dual-use goods"] },
  "050": { "name": "Bangladesh", "risk": 69, "issues": ["Under-invoicing", "Textile quota issues"] },
  "051": { "name": "Armenia", "risk": 39, "issues": ["Regional trade restrictions", "Certificates of origin"] },
  "052": { "name": "Barbados", "risk": 21, "issues": ["Tourism-related imports", "Occasional delays"] },
  "056": { "name": "Belgium", "risk": 38, "issues": ["Port of Antwerp congestion", "Transit delays"] },
  "060": { "name": "Bermuda", "risk": 50, "issues": [] },
  "064": { "name": "Bhutan", "risk": 50, "issues": [] },
  "068": { "name": "Bolivia", "risk": 55, "issues": ["Landlocked transport delays", "Documentation gaps"] },
  "070": { "name": "Bosnia and Herzegovina", "risk": 42, "issues": ["Regional trade barriers", "Origin rules"] },
  "072": { "name": "Botswana", "risk": 29, "issues": ["SADC harmonization", "Certificate of origin checks"] },
  "074": { "name": "Bouvet Island", "risk": 50, "issues": [] },
  "076": { "name": "Brazil", "risk": 65, "issues": ["Import license delays", "Documentation gaps"] },
  "084": { "name": "Belize", "risk": 30, "issues": ["Limited customs staff", "Occasional valuation issues"] },
  "086": { "name": "British Indian Ocean Territory", "risk": 50, "issues": [] },
  "090": { "name": "Solomon Islands", "risk": 37, "issues": ["Island logistics", "Customs inefficiencies"] },
  "092": { "name": "British Virgin Islands", "risk": 50, "issues": [] },
  "096": { "name": "Brunei Darussalam", "risk": 26, "issues": ["Oil export controls", "Customs valuation"] },
  "100": { "name": "Bulgaria", "risk": 43, "issues": ["EU harmonization", "VAT fraud monitoring"] },
  "104": { "name": "Myanmar", "risk": 76, "issues": ["Political instability", "Restricted imports"] },
  "108": { "name": "Burundi", "risk": 61, "issues": ["Weak border controls", "High paperwork load"] },
  "112": { "name": "Belarus", "risk": 81, "issues": ["Sanctions", "Restricted goods"] },
  "116": { "name": "Cambodia", "risk": 60, "issues": ["Frequent inspections", "Export certification delays"] },
  "120": { "name": "Cameroon", "risk": 64, "issues": ["Port clearance delays", "Under-invoicing"] },
  "124": { "name": "Canada", "risk": 33, "issues": ["NAFTA/USMCA rule changes"] },
  "132": { "name": "Cabo Verde", "risk": 22, "issues": ["Island logistics delays"] },
  "136": { "name": "Cayman Islands", "risk": 50, "issues": [] },
  "140": { "name": "Central African Republic", "risk": 74, "issues": ["Political instability", "Border issues"] },
  "144": { "name": "Sri Lanka", "risk": 50, "issues": [] },
  "148": { "name": "Chad", "risk": 72, "issues": ["Landlocked delays", "Weak border checks"] },
  "152": { "name": "Chile", "risk": 36, "issues": ["FTA adjustments", "Low risk overall"] },
  "156": { "name": "China", "risk": 75, "issues": ["Tariff misclassification", "Trade war duties"] },
  "158": { "name": "Taiwan", "risk": 40, "issues": ["Political tensions", "Export controls"] },
  "162": { "name": "Christmas Island", "risk": 50, "issues": [] },
  "166": { "name": "Cocos (Keeling) Islands", "risk": 50, "issues": [] },
  "170": { "name": "Colombia", "risk": 57, "issues": ["Drug-related inspections", "Frequent valuation checks"] },
  "174": { "name": "Comoros", "risk": 28, "issues": ["Small market", "Slow clearance"] },
  "175": { "name": "Mayotte", "risk": 50, "issues": [] },
  "178": { "name": "Congo", "risk": 63, "issues": ["Port delays", "Corruption risks"] },
  "180": { "name": "Democratic Republic of the Congo", "risk": 70, "issues": ["Infrastructure issues", "Customs inefficiencies"] },
  "184": { "name": "Cook Islands", "risk": 50, "issues": [] },
  "188": { "name": "Costa Rica", "risk": 44, "issues": ["FTA compliance", "Customs IT outages"] },
  "191": { "name": "Croatia", "risk": 41, "issues": ["EU harmonization issues", "VAT refunds"] },
  "192": { "name": "Cuba", "risk": 85, "issues": ["Sanctions", "Restricted goods"] },
  "196": { "name": "Cyprus", "risk": 35, "issues": ["Freeport checks", "Occasional delays"] },
  "203": { "name": "Czechia", "risk": 37, "issues": ["Low compliance risk"] },
  "204": { "name": "Benin", "risk": 50, "issues": [] },
  "208": { "name": "Denmark", "risk": 31, "issues": ["Low risk", "Occasional VAT disputes"] },
  "212": { "name": "Dominica", "risk": 23, "issues": ["Small volume", "Tourism imports"] },
  "214": { "name": "Dominican Republic", "risk": 53, "issues": ["Tourism-related imports", "Port delays"] },
  "218": { "name": "Ecuador", "risk": 56, "issues": ["Oil exports", "Customs clearance delays"] },
  "222": { "name": "El Salvador", "risk": 49, "issues": ["CAFTA issues", "Documentation errors"] },
  "226": { "name": "Equatorial Guinea", "risk": 65, "issues": ["Oil-related trade disputes", "Port congestion"] },
  "231": { "name": "Ethiopia", "risk": 70, "issues": ["Landlocked delays", "Customs inefficiencies"] },
  "232": { "name": "Eritrea", "risk": 78, "issues": ["Trade restrictions", "Political instability"] },
  "233": { "name": "Estonia", "risk": 28, "issues": ["Low risk", "Occasional VAT handling"] },
  "234": { "name": "Faroe Islands", "risk": 50, "issues": [] },
  "238": { "name": "Falkland Islands (Malvinas)", "risk": 50, "issues": [] },
  "239": { "name": "South Georgia and the South Sandwich Islands", "risk": 50, "issues": [] },
  "242": { "name": "Fiji", "risk": 34, "issues": ["Island logistics", "Tourism imports"] },
  "246": { "name": "Finland", "risk": 29, "issues": ["Low risk", "Occasional valuation issues"] },
  "250": { "name": "France", "risk": 41, "issues": ["Valuation adjustments", "Certificate of origin issues"] },
  "254": { "name": "French Guiana", "risk": 50, "issues": [] },
  "258": { "name": "French Polynesia", "risk": 50, "issues": [] },
  "260": { "name": "French Southern Territories", "risk": 50, "issues": [] },
  "262": { "name": "Djibouti", "risk": 60, "issues": ["Port dependency", "Regional security"] },
  "266": { "name": "Gabon", "risk": 62, "issues": ["Port congestion", "Export checks"] },
  "268": { "name": "Georgia", "risk": 47, "issues": ["Transit issues", "Certificates of origin"] },
  "270": { "name": "Gambia", "risk": 51, "issues": ["Port delays", "Documentation errors"] },
  "275": { "name": "Palestine, State of", "risk": 50, "issues": [] },
  "276": { "name": "Germany", "risk": 82, "issues": ["HS code errors", "Delayed filings"] },
  "288": { "name": "Ghana", "risk": 59, "issues": ["Port congestion", "Under-invoicing"] },
  "292": { "name": "Gibraltar", "risk": 50, "issues": [] },
  "296": { "name": "Kiribati", "risk": 50, "issues": [] },
  "300": { "name": "Greece", "risk": 50, "issues": ["EU VAT disputes", "Port strikes"] },
  "304": { "name": "Greenland", "risk": 50, "issues": [] },
  "308": { "name": "Grenada", "risk": 20, "issues": ["Small trade volume"] },
  "312": { "name": "Guadeloupe", "risk": 50, "issues": [] },
  "316": { "name": "Guam", "risk": 50, "issues": [] },
  "320": { "name": "Guatemala", "risk": 55, "issues": ["Border inspections", "Documentation issues"] },
  "324": { "name": "Guinea", "risk": 64, "issues": ["Port inefficiencies", "Mining exports delays"] },
  "328": { "name": "Guyana", "risk": 40, "issues": ["New oil exports", "Valuation issues"] },
  "332": { "name": "Haiti", "risk": 76, "issues": ["Political instability", "Port congestion"] },
  "334": { "name": "Heard Island and McDonald Islands", "risk": 50, "issues": [] },
  "336": { "name": "Holy See", "risk": 50, "issues": [] },
  "340": { "name": "Honduras", "risk": 52, "issues": ["CAFTA issues", "Documentation gaps"] },
  "344": { "name": "Hong Kong", "risk": 50, "issues": [] },
  "348": { "name": "Hungary", "risk": 39, "issues": ["EU harmonization", "VAT fraud monitoring"] },
  "352": { "name": "Iceland", "risk": 25, "issues": ["Low trade risk", "Occasional customs IT delays"] },
  "356": { "name": "India", "risk": 47, "issues": ["Valuation disputes", "Missing certificates"] },
  "360": { "name": "Indonesia", "risk": 61, "issues": ["Import license restrictions", "Customs clearance delays"] },
  "364": { "name": "Iran", "risk": 91, "issues": ["Sanctions", "Restricted goods"] },
  "368": { "name": "Iraq", "risk": 79, "issues": ["Security checks", "Port congestion"] },
  "372": { "name": "Ireland", "risk": 33, "issues": ["EU compliance", "Low risk overall"] },
  "376": { "name": "Israel", "risk": 46, "issues": ["Security-related delays", "Origin disputes"] },
  "380": { "name": "Italy", "risk": 42, "issues": ["EU VAT disputes", "Port congestion"] },
  "384": { "name": "Côte d'Ivoire", "risk": 54, "issues": ["Export controls", "Port congestion"] },
  "388": { "name": "Jamaica", "risk": 45, "issues": ["Tourism imports", "Documentation gaps"] },
  "392": { "name": "Japan", "risk": 28, "issues": ["Low risk", "Occasional customs paperwork"] },
  "398": { "name": "Kazakhstan", "risk": 60, "issues": ["Eurasian Customs Union rules", "Transit issues"] },
  "400": { "name": "Jordan", "risk": 57, "issues": ["Import licensing", "Border inspections"] },
  "404": { "name": "Kenya", "risk": 63, "issues": ["Port delays", "Under-invoicing"] },
  "408": { "name": "Korea, North", "risk": 95, "issues": ["Sanctions", "Restricted goods"] },
  "410": { "name": "Korea, South", "risk": 31, "issues": ["FTA compliance", "Low risk overall"] },
  "414": { "name": "Kuwait", "risk": 38, "issues": ["Oil exports", "Documentation checks"] },
  "417": { "name": "Kyrgyzstan", "risk": 49, "issues": ["Transit delays", "Regional trade barriers"] },
  "418": { "name": "Lao PDR", "risk": 62, "issues": ["Landlocked delays", "Customs inefficiencies"] },
  "422": { "name": "Lebanon", "risk": 78, "issues": ["Port congestion", "Currency restrictions"] },
  "426": { "name": "Lesotho", "risk": 44, "issues": ["Landlocked transport", "Limited customs staff"] },
  "428": { "name": "Latvia", "risk": 27, "issues": ["Low risk", "EU compliance"] },
  "430": { "name": "Liberia", "risk": 66, "issues": ["Port delays", "Paperwork inefficiencies"] },
  "434": { "name": "Libya", "risk": 84, "issues": ["Political instability", "Sanctions"] },
  "438": { "name": "Liechtenstein", "risk": 22, "issues": ["Low volume trade", "Occasional customs errors"] },
  "440": { "name": "Lithuania", "risk": 28, "issues": ["Low risk", "EU harmonization"] },
  "442": { "name": "Luxembourg", "risk": 25, "issues": ["Low trade volume", "Occasional documentation delays"] },
  "446": { "name": "Macao", "risk": 50, "issues": [] },
  "450": { "name": "Madagascar", "risk": 61, "issues": ["Island logistics", "Port congestion"] },
  "454": { "name": "Malawi", "risk": 58, "issues": ["Landlocked delays", "Customs inefficiencies"] },
  "458": { "name": "Malaysia", "risk": 34, "issues": ["FTA compliance", "Occasional paperwork errors"] },
  "462": { "name": "Maldives", "risk": 29, "issues": ["Island logistics", "Small trade volume"] },
  "466": { "name": "Mali", "risk": 63, "issues": ["Landlocked transport", "Smuggling risks"] },
  "470": { "name": "Malta", "risk": 27, "issues": ["Low risk", "EU harmonization"] },
  "474": { "name": "Mauritania", "risk": 67, "issues": ["Port congestion", "Documentation gaps"] },
  "478": { "name": "Mauritius", "risk": 32, "issues": ["Island logistics", "Low trade risk"] },
  "480": { "name": "Micronesia", "risk": 22, "issues": ["Small trade volume"] },
  "484": { "name": "Mexico", "risk": 46, "issues": ["NAFTA/USMCA compliance", "Documentation issues"] },
  "492": { "name": "Monaco", "risk": 20, "issues": ["Low risk", "Occasional customs checks"] },
  "496": { "name": "Mongolia", "risk": 55, "issues": ["Landlocked transport", "Customs inefficiencies"] },
  "498": { "name": "Moldova", "risk": 48, "issues": ["Regional transit issues", "Documentation delays"] },
  "499": { "name": "Montenegro", "risk": 41, "issues": ["Regional trade barriers", "Documentation gaps"] },
  "500": { "name": "Montserrat", "risk": 50, "issues": [] },
  "504": { "name": "Morocco", "risk": 52, "issues": ["Port congestion", "Import licensing"] },
  "508": { "name": "Mozambique", "risk": 65, "issues": ["Port delays", "Customs paperwork"] },
  "512": { "name": "Oman", "risk": 35, "issues": ["Oil exports", "Documentation checks"] },
  "516": { "name": "Namibia", "risk": 42, "issues": ["SADC compliance", "Customs delays"] },
  "520": { "name": "Nauru", "risk": 18, "issues": ["Very low trade volume"] },
  "524": { "name": "Nepal", "risk": 54, "issues": ["Landlocked delays", "Documentation inefficiencies"] },
  "528": { "name": "Netherlands", "risk": 31, "issues": ["Port congestion", "EU compliance"] },
  "531": { "name": "Curaçao", "risk": 50, "issues": [] },
  "533": { "name": "Aruba", "risk": 50, "issues": [] },
  "534": { "name": "Sint Maarten (Dutch part)", "risk": 50, "issues": [] },
  "535": { "name": "Bonaire, Sint Eustatius and Saba", "risk": 50, "issues": [] },
  "540": { "name": "Nicaragua", "risk": 56, "issues": ["Border inspections", "Documentation gaps"] },
  "548": { "name": "Vanuatu", "risk": 50, "issues": [] },
  "554": { "name": "New Zealand", "risk": 29, "issues": ["Low risk", "Occasional biosecurity checks"] },
  "558": { "name": "Nicaragua", "risk": 50, "issues": [] },
  "562": { "name": "Niger", "risk": 68, "issues": ["Landlocked transport", "Weak customs infrastructure"] },
  "566": { "name": "Nigeria", "risk": 71, "issues": ["Port congestion", "Under-invoicing"] },
  "570": { "name": "Niue", "risk": 21, "issues": ["Small trade volume"] },
  "574": { "name": "Norfolk Island", "risk": 50, "issues": [] },
  "578": { "name": "Norway", "risk": 30, "issues": ["Low risk", "Occasional valuation issues", "Trolls interfering with shipments"] },
  "580": { "name": "Northern Mariana Islands", "risk": 50, "issues": [] },
  "581": { "name": "United States Minor Outlying Islands", "risk": 50, "issues": [] },
  "583": { "name": "Micronesia (Federated States of)", "risk": 50, "issues": [] },
  "584": { "name": "Marshall Islands", "risk": 23, "issues": ["Small market", "Occasional port delays"] },
  "585": { "name": "Palau", "risk": 50, "issues": [] },
  "586": { "name": "Pakistan", "risk": 50, "issues": [] },
  "591": { "name": "Romania", "risk": 44, "issues": ["EU harmonization", "VAT monitoring"] },
  "598": { "name": "Papua New Guinea", "risk": 48, "issues": ["Port congestion", "Documentation gaps"] },
  "600": { "name": "Paraguay", "risk": 53, "issues": ["Landlocked delays", "Customs inefficiencies"] },
  "604": { "name": "Peru", "risk": 37, "issues": ["Port congestion", "Documentation gaps"] },
  "608": { "name": "Philippines", "risk": 50, "issues": ["Island logistics", "Frequent inspections"] },
  "612": { "name": "Pitcairn", "risk": 50, "issues": [] },
  "616": { "name": "Poland", "risk": 37, "issues": ["EU compliance", "VAT adjustments"] },
  "620": { "name": "Portugal", "risk": 36, "issues": ["EU compliance", "Occasional port delays"] },
  "624": { "name": "Guinea-Bissau", "risk": 65, "issues": ["Weak customs infrastructure"] },
  "626": { "name": "Timor-Leste", "risk": 40, "issues": ["Island logistics", "Customs inefficiencies"] },
  "630": { "name": "Puerto Rico", "risk": 50, "issues": [] },
  "634": { "name": "Qatar", "risk": 34, "issues": ["Oil exports", "Customs paperwork"] },
  "638": { "name": "Réunion", "risk": 50, "issues": [] },
  "642": { "name": "Saudi Arabia", "risk": 45, "issues": ["Oil exports", "Import licensing"] },
  "643": { "name": "Russia", "risk": 82, "issues": ["Sanctions", "Trade restrictions"] },
  "646": { "name": "Rwanda", "risk": 48, "issues": ["Landlocked transport", "Customs delays"] },
  "652": { "name": "Saint Barthélemy", "risk": 50, "issues": [] },
  "654": { "name": "Saint Helena, Ascension and Tristan da Cunha", "risk": 50, "issues": [] },
  "659": { "name": "Saint Kitts and Nevis", "risk": 50, "issues": [] },
  "660": { "name": "Anguilla", "risk": 50, "issues": [] },
  "662": { "name": "Samoa", "risk": 27, "issues": ["Island logistics"] },
  "663": { "name": "Saint Martin (French part)", "risk": 50, "issues": [] },
  "666": { "name": "Saint Pierre and Miquelon", "risk": 50, "issues": [] },
  "670": { "name": "Saint Vincent and the Grenadines", "risk": 50, "issues": [] },
  "674": { "name": "San Marino", "risk": 20, "issues": ["Very low trade volume"] },
  "678": { "name": "Sao Tome and Principe", "risk": 33, "issues": ["Island logistics", "Customs inefficiencies"] },
  "682": { "name": "Saudi Arabia", "risk": 45, "issues": ["Oil exports", "Import licensing"] },
  "686": { "name": "Senegal", "risk": 50, "issues": [] },
  "688": { "name": "Serbia", "risk": 47, "issues": ["Regional trade barriers", "Documentation gaps"] },
  "690": { "name": "Seychelles", "risk": 30, "issues": ["Island logistics", "Small trade volume"] },
  "694": { "name": "Sierra Leone", "risk": 50, "issues": [] },
  "702": { "name": "Singapore", "risk": 50, "issues": [] },
  "703": { "name": "Slovakia", "risk": 50, "issues": [] },
  "704": { "name": "Somalia", "risk": 88, "issues": ["Political instability", "Piracy risk"] },
  "705": { "name": "Slovenia", "risk": 27, "issues": ["EU compliance", "Occasional documentation delays"] },
  "706": { "name": "Somalia", "risk": 50, "issues": [] },
  "710": { "name": "South Africa", "risk": 50, "issues": ["Port congestion", "Customs delays"] },
  "724": { "name": "Spain", "risk": 46, "issues": ["Documentation delays", "Incorrect HS codes"] },
  "728": { "name": "South Sudan", "risk": 92, "issues": ["Political instability", "Border conflicts"] },
  "729": { "name": "Sudan", "risk": 85, "issues": ["Political instability", "Humanitarian issues"] },
  "732": { "name": "Western Sahara", "risk": 50, "issues": [] },
  "740": { "name": "Suriname", "risk": 50, "issues": [] },
  "744": { "name": "Svalbard and Jan Mayen", "risk": 50, "issues": [] },
  "748": { "name": "Eswatini", "risk": 50, "issues": [] },
  "752": { "name": "Sweden", "risk": 29, "issues": ["EU compliance", "Low risk"] },
  "756": { "name": "Switzerland", "risk": 27, "issues": ["EU compliance", "Low risk"] },
  "760": { "name": "Syria", "risk": 85, "issues": ["Sanctions", "Political instability"] },
  "762": { "name": "Tajikistan", "risk": 52, "issues": ["Landlocked challenges", "Customs inefficiencies"] },
  "764": { "name": "Thailand", "risk": 35, "issues": ["Customs delays", "Documentation issues"] },
  "768": { "name": "Togo", "risk": 45, "issues": ["Port congestion", "Customs delays"] },
  "772": { "name": "Tokelau", "risk": 50, "issues": [] },
  "776": { "name": "Tonga", "risk": 30, "issues": ["Island logistics", "Small trade volume"] },
  "780": { "name": "Trinidad and Tobago", "risk": 32, "issues": ["Island logistics", "Customs inefficiencies"] },
  "784": { "name": "United Arab Emirates", "risk": 50, "issues": [] },
  "788": { "name": "Tunisia", "risk": 42, "issues": ["Customs delays", "Documentation issues"] },
  "792": { "name": "Turkey", "risk": 50, "issues": ["Customs delays", "Political tensions"] },
  "795": { "name": "Turkmenistan", "risk": 60, "issues": ["Landlocked challenges", "Customs inefficiencies"] },
  "796": { "name": "Turks and Caicos Islands", "risk": 50, "issues": [] },
  "798": { "name": "Tuvalu", "risk": 50, "issues": [] },
  "800": { "name": "Uganda", "risk": 50, "issues": [] },
  "804": { "name": "Ukraine", "risk": 50, "issues": [] },
  "807": { "name": "North Macedonia", "risk": 50, "issues": [] },
  "818": { "name": "Egypt", "risk": 67, "issues": ["Port congestion", "Currency restrictions"] },
  "826": { "name": "United Kingdom", "risk": 68, "issues": ["Post-Brexit customs checks", "Delays at ports"] },
  "831": { "name": "Guernsey", "risk": 50, "issues": [] },
  "832": { "name": "Jersey", "risk": 50, "issues": [] },
  "833": { "name": "Isle of Man", "risk": 50, "issues": [] },
  "834": { "name": "Tanzania, United Republic of", "risk": 50, "issues": [] },
  "840": { "name": "United States", "risk": 90, "issues": ["Audit findings", "Incorrect origin rules", "Item 3", "Item 4", "Item 5"] },
  "850": { "name": "United States Virgin Islands", "risk": 50, "issues": [] },
  "854": { "name": "Burkina Faso", "risk": 59, "issues": ["Landlocked delays", "Smuggling risks"] },
  "858": { "name": "Uruguay", "risk": 50, "issues": [] },
  "860": { "name": "Uzbekistan", "risk": 50, "issues": [] },
  "862": { "name": "Venezuela", "risk": 90, "issues": ["Political instability", "Economic sanctions"] },
  "876": { "name": "Wallis and Futuna", "risk": 50, "issues": [] },
  "882": { "name": "Samoa", "risk": 50, "issues": [] },
  "887": { "name": "Yemen", "risk": 50, "issues": [] },
  "894": { "name": "Zambia", "risk": 50, "issues": [] },
  "716": { "name": "Zimbabwe", "risk": 75, "issues": ["Political instability", "Economic challenges"] }

}
